emojiextension.py
markdown_emojiextension-1.2.dist-info/LICENSE
markdown_emojiextension-1.2.dist-info/METADATA
markdown_emojiextension-1.2.dist-info/WHEEL
markdown_emojiextension-1.2.dist-info/top_level.txt
markdown_emojiextension-1.2.dist-info/RECORD
