Metadata-Version: 2.1
Name: markdown-emojiextension
Version: 1.2
Summary: Extension for displaying Emojis in MArkdown
Home-page: UNKNOWN
Author: UNKNOWN
Author-email: UNKNOWN
License: UNKNOWN
Platform: UNKNOWN
Requires-Dist: markdown (>=3.3)
